catwalk/__init__.py
catwalk/__main__.py
catwalk/cached_transformers.py
catwalk/model.py
catwalk/py.typed
catwalk/steps.py
catwalk/task.py
catwalk/train.py
catwalk/training_callback.py
catwalk/version.py
catwalk/dependencies/__init__.py
catwalk/dependencies/lm_eval/__init__.py
catwalk/dependencies/lm_eval/base.py
catwalk/dependencies/lm_eval/evaluator.py
catwalk/dependencies/lm_eval/metrics.py
catwalk/dependencies/lm_eval/utils.py
catwalk/dependencies/lm_eval/datasets/__init__.py
catwalk/dependencies/lm_eval/datasets/arithmetic/__init__.py
catwalk/dependencies/lm_eval/datasets/arithmetic/arithmetic.py
catwalk/dependencies/lm_eval/datasets/asdiv/__init__.py
catwalk/dependencies/lm_eval/datasets/asdiv/asdiv.py
catwalk/dependencies/lm_eval/datasets/coqa/__init__.py
catwalk/dependencies/lm_eval/datasets/coqa/coqa.py
catwalk/dependencies/lm_eval/datasets/drop/__init__.py
catwalk/dependencies/lm_eval/datasets/drop/drop.py
catwalk/dependencies/lm_eval/datasets/headqa/__init__.py
catwalk/dependencies/lm_eval/datasets/headqa/headqa.py
catwalk/dependencies/lm_eval/datasets/hendrycks_ethics/__init__.py
catwalk/dependencies/lm_eval/datasets/hendrycks_ethics/hendrycks_ethics.py
catwalk/dependencies/lm_eval/datasets/hendrycks_math/__init__.py
catwalk/dependencies/lm_eval/datasets/hendrycks_math/hendrycks_math.py
catwalk/dependencies/lm_eval/datasets/lambada_openai/__init__.py
catwalk/dependencies/lm_eval/datasets/lambada_openai/lambada_openai.py
catwalk/dependencies/lm_eval/datasets/logiqa/__init__.py
catwalk/dependencies/lm_eval/datasets/logiqa/logiqa.py
catwalk/dependencies/lm_eval/datasets/mutual/__init__.py
catwalk/dependencies/lm_eval/datasets/mutual/mutual.py
catwalk/dependencies/lm_eval/datasets/pile/__init__.py
catwalk/dependencies/lm_eval/datasets/pile/pile.py
catwalk/dependencies/lm_eval/datasets/quac/__init__.py
catwalk/dependencies/lm_eval/datasets/quac/quac.py
catwalk/dependencies/lm_eval/datasets/sat_analogies/__init__.py
ai2_catwalk-0.2.2.dist-info/LICENSE
ai2_catwalk-0.2.2.dist-info/METADATA
ai2_catwalk-0.2.2.dist-info/WHEEL
ai2_catwalk-0.2.2.dist-info/top_level.txt
ai2_catwalk-0.2.2.dist-info/RECORD
