Metadata-Version: 2.1
Name: ai2-catwalk
Version: 0.2.2
Summary: A library for evaluating language models.
Home-page: https://github.com/allenai/catwalk
Author: Allen Institute for Artificial Intelligence
Author-email: contact@allenai.org
License: Apache
Classifier: Intended Audience :: Science/Research
Classifier: Development Status :: 3 - Alpha
Classifier: License :: OSI Approved :: Apache Software License
Classifier: Programming Language :: Python :: 3
Classifier: Topic :: Scientific/Engineering :: Artificial Intelligence
Requires-Python: >=3.8.0
License-File: LICENSE
Requires-Dist: ai2-tango[beaker,fairscale,torch,transformers,wandb] (>=1.1)
Requires-Dist: torchmetrics (==0.11.0)
Requires-Dist: more-itertools
Requires-Dist: spacy (>=3.0.0)
Requires-Dist: wget
Requires-Dist: datasets (>=2.1.0)
Requires-Dist: accelerate
Requires-Dist: bettermap
Requires-Dist: sacrebleu (>=1.5.0)
Requires-Dist: scikit-learn (>=0.24.1)
Requires-Dist: pycountry (>=20.7.3)
Requires-Dist: rouge-score (>=0.0.4)
Requires-Dist: tensorflow
Requires-Dist: mypy-extensions
Requires-Dist: pytest
Requires-Dist: jinja2
Requires-Dist: pyyaml (>=5)
Provides-Extra: dev
Requires-Dist: mypy ; extra == 'dev'
Requires-Dist: twine (>=1.11.0) ; extra == 'dev'
Requires-Dist: setuptools ; extra == 'dev'
Requires-Dist: wheel ; extra == 'dev'
Requires-Dist: packaging ; extra == 'dev'
Requires-Dist: pytest (>=6.2.5) ; extra == 'dev'
Requires-Dist: pytest-sphinx ; extra == 'dev'
Requires-Dist: pytest-xdist ; extra == 'dev'
Requires-Dist: pytest-forked ; extra == 'dev'
Requires-Dist: flaky ; extra == 'dev'
Requires-Dist: Sphinx (==5.3.0) ; extra == 'dev'
Requires-Dist: furo (==2022.12.7) ; extra == 'dev'
Requires-Dist: myst-parser (==0.18.1) ; extra == 'dev'
Requires-Dist: sphinx-copybutton (==0.5.1) ; extra == 'dev'
Requires-Dist: sphinx-autobuild (==2021.3.14) ; extra == 'dev'
Requires-Dist: sphinx-autodoc-typehints ; extra == 'dev'
